aplotly/__init__.py
aplotly/colors.py
aplotly/io.py
aplotly/plots.py
aplotly/style.py
aplotly/utils/return_breakdown.py
aplotly-1.1.25.dist-info/licenses/LICENSE
aplotly-1.1.25.dist-info/METADATA
aplotly-1.1.25.dist-info/WHEEL
aplotly-1.1.25.dist-info/top_level.txt
aplotly-1.1.25.dist-info/RECORD
