Metadata-Version: 2.4
Name: aplotly
Version: 1.1.25
License: MIT License
Classifier: License :: OSI Approved :: MIT License
Classifier: Programming Language :: Python
Classifier: Programming Language :: Python :: 3
Requires-Python: >=3.10
License-File: LICENSE
Requires-Dist: plotly>=5.18.0
Requires-Dist: pandas>=2.1.3
Dynamic: license-file
